{
  "schema": "lanlink-config-v2.2",
  "listen_port": 57222,
  "preferred_ip": "",
  "max_message_bytes": 65536,
  "file_chunk_bytes": 196608,
  "connect_timeout_ms": 5000,
  "io_timeout_ms": 30000,
  "tcp_keepalive_time_ms": 15000,
  "tcp_keepalive_interval_ms": 5000,
  "max_session_seconds": 3600,
  "max_session_requests": 20000,
  "min_free_space_mb": 1024,
  "retry_jitter_percent": 25,
  "max_clock_skew_seconds": 600,
  "sent_receipt_days": 30,
  "replay_retention_days": 7,
  "dedupe_retention_days": 90,
  "invite_retention_days": 2,
  "log_retention_days": 14,
  "max_log_files": 20,
  "max_pending_messages": 500,
  "max_pending_files": 100,
  "max_diag_inventory_files": 5000,
  "max_diag_seconds": 10
}
